setup.py
toutf8/__init__.py
toutf8.egg-info/PKG-INFO
toutf8.egg-info/SOURCES.txt
toutf8.egg-info/dependency_links.txt
toutf8.egg-info/entry_points.txt
toutf8.egg-info/requires.txt
toutf8.egg-info/top_level.txt