Metadata-Version: 1.0
Name: toutf8
Version: 1.3.0
Summary: A tool to change all files in specified folder to utf-8 encoding
Home-page: https://github.com/liangsun/toutf8
Author: 1e0n
Author-email: i@leons.im
License: http://www.apache.org/licenses/LICENSE-2.0
Keywords: utf8 encoding gbk gb2312 shiftjis ascii gb18030
Platform: UNKNOWN
